odoo8_addon_mass_sorting-8.0.1.0.0.99.dev2-py2.7-nspkg.pth
odoo8_addon_mass_sorting-8.0.1.0.0.99.dev2.dist-info/DESCRIPTION.rst
odoo8_addon_mass_sorting-8.0.1.0.0.99.dev2.dist-info/METADATA
odoo8_addon_mass_sorting-8.0.1.0.0.99.dev2.dist-info/RECORD
odoo8_addon_mass_sorting-8.0.1.0.0.99.dev2.dist-info/WHEEL
odoo8_addon_mass_sorting-8.0.1.0.0.99.dev2.dist-info/metadata.json
odoo8_addon_mass_sorting-8.0.1.0.0.99.dev2.dist-info/namespace_packages.txt
odoo8_addon_mass_sorting-8.0.1.0.0.99.dev2.dist-info/top_level.txt
odoo_addons/mass_sorting/README.rst
odoo_addons/mass_sorting/__init__.py
odoo_addons/mass_sorting/__openerp__.py
odoo_addons/mass_sorting/demo/function.xml
odoo_addons/mass_sorting/demo/mass_sort_config.xml
odoo_addons/mass_sorting/demo/mass_sort_config_line.xml
odoo_addons/mass_sorting/i18n/fr.po
odoo_addons/mass_sorting/i18n/mass_sorting.pot
odoo_addons/mass_sorting/models/__init__.py
odoo_addons/mass_sorting/models/mass_sort_config.py
odoo_addons/mass_sorting/models/mass_sort_config_line.py
odoo_addons/mass_sorting/models/mass_sort_wizard.py
odoo_addons/mass_sorting/models/mass_sort_wizard_line.py
odoo_addons/mass_sorting/security/ir.model.access.csv
odoo_addons/mass_sorting/static/description/1_mass_sort_config.png
odoo_addons/mass_sorting/static/description/2_button.png
odoo_addons/mass_sorting/static/description/3_mass_sort_wizard.png
odoo_addons/mass_sorting/static/description/3_mass_sort_wizard_custom.png
odoo_addons/mass_sorting/static/description/4_before.png
odoo_addons/mass_sorting/static/description/5_after.png
odoo_addons/mass_sorting/static/description/icon.png
odoo_addons/mass_sorting/views/action.xml
odoo_addons/mass_sorting/views/menu.xml
odoo_addons/mass_sorting/views/view_mass_sort_config.xml
odoo_addons/mass_sorting/views/view_mass_sort_wizard.xml
